<item>
<title>[COLORblue]Some Of The Live Channels May Not Work But The Rest Does[/COLOR]</title>
<link>IGNOREME</link>
<thumbnail></thumbnail>
<fanart></fanart>
</item>

<item>
<title>[COLORred]BBC IPlayer WWW[/COLOR]</title>
<link>IGNOREME</link>
<jsonrpc>plugin://plugin.video.iplayerwww/</jsonrpc>
<thumbnail>https://i.imgur.com/iHZ9TU9.jpg</thumbnail>
<fanart></fanart>
</item>

<item>
<title>[COLORred]ITV Player[/COLOR]</title>
<link>IGNOREME</link>
<jsonrpc>plugin://plugin.video.itv/</jsonrpc>
<thumbnail>https://i.imgur.com/iHZ9TU9.jpg</thumbnail>
<fanart></fanart>
</item>

<item>
<title>[COLORred]NASA TV Live[/COLOR]</title>
<link>IGNOREME</link>
<jsonrpc>plugin://plugin.video.nasa/</jsonrpc>
<thumbnail>https://i.imgur.com/iHZ9TU9.jpg</thumbnail>
<fanart></fanart>
</item>

<item>
<title>[COLORred]Nat Geo TV[/COLOR]</title>
<link>IGNOREME</link>
<jsonrpc>plugin://plugin.video.ng/</jsonrpc>
<thumbnail>https://i.imgur.com/iHZ9TU9.jpg</thumbnail>
<fanart></fanart>
</item>

<item>
<title>[COLORred]Sky News[/COLOR]</title>
<link>IGNOREME</link>
<jsonrpc>plugin://plugin.video.skynews/</jsonrpc>
<thumbnail>https://i.imgur.com/iHZ9TU9.jpg</thumbnail>
<fanart></fanart>
</item>

<item>
<title>[COLORred]Spurs TV[/COLOR]</title>
<link>IGNOREME</link>
<jsonrpc>plugin://plugin.video.spurs-tv/</jsonrpc>
<thumbnail>https://i.imgur.com/iHZ9TU9.jpg</thumbnail>
<fanart></fanart>
</item>
