<item>
<title>[COLORblue][B]****All Free Links - 1080p When Possible****[/B][/COLOR]</title>
<link>ignoreme</link>
<thumbnail>https://i.imgur.com/r6nMlcQ.png</thumbnail>
<fanart></fanart>
</item>
 
<item>
<title>[COLORyellow][B]*****Updated Daily*****[/B][/COLOR]</title>
<link>ignoreme</link>
<thumbnail>https://i.imgur.com/r6nMlcQ.png</thumbnail>
<fanart></fanart>
</item>

<item>
<title>Don't Click (2020) (2020) [COLORblue]4.1-Horror[/COLOR]</title>
<link>https://mixdrop.co/f/enl39kgvcekrqe</link>
<thumbnail>https://i.postimg.cc/1RkJwyKs/tmpposter20441.jpg</thumbnail>
<fanart></fanart>
</item>

<item>
<title>We Still Say Grace (2020) [COLORblue]Thriller[/COLOR]</title>
<link>https://mixdrop.co/f/84lzgwrmsdpe6k</link>
<thumbnail>https://i.postimg.cc/5NCGwdmw/tmpposter16657.jpg</thumbnail>
<fanart></fanart>
</item>

<item>
<title>Parallel (2018) [COLORblue]6.4-Drama/Thriller[/COLOR]</title>
<link>https://mixdrop.co/f/dqkg96vdigk0wj</link>
<thumbnail>https://i.postimg.cc/L4jJqh1R/tmpposter17954.jpg</thumbnail>
<fanart></fanart>
</item>

<item>
<title>Wander Darkly (2020) [COLORblue]6.1-Drama[/COLOR]</title>
<link>https://mixdrop.co/f/l67po11vhq1ogk8</link>
<thumbnail>https://i.postimg.cc/Yqwm8QHh/tmpposter3550.jpg</thumbnail>
<fanart></fanart>
</item>

<item>
<title>Archenemy (2020) [COLORblue]5.7-Action/Adventure[/COLOR]</title>
<link>https://mixdrop.co/f/o7w0omrqfxgj7n</link>
<thumbnail>https://i.postimg.cc/G2pyFKPD/tmpposter27024.jpg</thumbnail>
<fanart></fanart>
</item>

<item>
<title>The Stand In (2020) [COLORblue]Comedy[/COLOR]</title>
<link>https://mixdrop.co/f/j9doewevhw37k0</link>
<thumbnail>https://i.postimg.cc/Jhfy98j1/tmpposter11121.jpg</thumbnail>
<fanart></fanart>
</item>

<item>
<title>Battle of the Bulge: Winter War (2020) [COLORblue]4.0-War[/COLOR]</title>
<link>https://mixdrop.co/f/ql1kz04qhn709z</link>
<thumbnail>https://i.postimg.cc/qvfWy6rJ/tmpposter23437.jpg</thumbnail>
<fanart></fanart>
</item>

<item>
<title>I'm Your Woman (2020) [COLORblue]6.0-Crime/Drama[/COLOR]</title>
<link>https://mixdrop.co/f/ql1kz48ebxxqz4r</link>
<thumbnail>https://i.postimg.cc/9Mfykzcs/tmpposter20056.jpg</thumbnail>
<fanart></fanart>
</item>

<item>
<title>Songbird (2020) [COLORblue]Comedy/Drama/Romance/Thriller[/COLOR]</title>
<link>https://mixdrop.co/f/pkj7xr4ltgwo1vr</link>
<thumbnail>https://i.postimg.cc/J4CGDt9m/tmpposter27795.jpg</thumbnail>
<fanart></fanart>
</item>

<item>
<title>Dr. Seuss' the Grinch Musical (2020)</title>
<link>https://mixdrop.co/f/pkj7xrkpt4w9po</link>
<thumbnail>https://i.postimg.cc/NjVDm6YL/759b555b16a64fcabb3c839a8060b269741f8947.jpg</thumbnail>
<fanart></fanart>
</item>

<item>
<title>Dr. Seuss' the Grinch (2018)</title>
<link>https://aparat.cam/1boeoz1et945</link>
<thumbnail>https://i.postimg.cc/XJR16tQf/poster-opt.jpg</thumbnail>
<fanart></fanart>
</item>

<item>
<title>How the Grinch Stole Christmas (2000)</title>
<link>https://aparat.cam/4dkqyrwkmyi3</link>
<thumbnail>https://i.postimg.cc/RFRX6qR0/poster-opt.jpg</thumbnail>
<fanart></fanart>
</item>

<item>
<title>Maybe Tomorrow (2020) [COLORblue]Drama/Short[/COLOR]</title>
<link>https://aparat.cam/mzmgmy6gh9gd</link>
<thumbnail>https://i.postimg.cc/vmgS4YHM/poster-opt.jpg</thumbnail>
<fanart></fanart>
</item>

<item>
<title>Savage (2019) [COLORblue]7.1-Crime/Drama[/COLOR]</title>
<link>https://mixdrop.co/f/j9domjgxt77680m</link>
<thumbnail>https://i.postimg.cc/TwTYR4fV/tmpposter5578.jpg</thumbnail>
<fanart></fanart>
</item>

<item>
<title>Let Them All Talk (2020) [COLORblue]Comedy/Drama[/COLOR]</title>
<link>https://streamtape.com/v/4oOJ94JjGRuKwpj</link>
<thumbnail>https://i.postimg.cc/mDtk1Q35/tmpposter12182.jpg</thumbnail>
<fanart></fanart>
</item>

<item>
<title>Wild Mountain Thyme (2020) [COLORblue]Drama/Romance[/COLOR]</title>
<link>https://mixdrop.co/f/6q71387gtl41dp0</link>
<thumbnail>https://i.postimg.cc/g2ZxNyfF/tmpposter15443.jpg</thumbnail>
<fanart></fanart>
</item>

<item>
<title>Alabama Snake (2020) [COLORblue]7.2-Crime/Docu.[/COLOR]</title>
<link>https://aparat.cam/3zl82jugxh61</link>
<thumbnail>https://i.postimg.cc/prTqRRcN/poster-opt.jpg</thumbnail>
<fanart></fanart>
</item>

<item>
<title>Die Hard (1988) [COLORblue]Best Christmas Movie Ever[/COLOR]</title>
<link>https://aparat.cam/pfsqumpynsi6</link>
<thumbnail>https://i.postimg.cc/HWFH8Rp4/poster-opt.jpg</thumbnail>
<fanart></fanart>
</item>

<item>
<title>Last Christmas (2019) [COLORblue]Comedy/Drama/Romance/Queen Of Dragons[/COLOR]</title>
<link>https://aparat.cam/i7ksfb0s1a7i</link>
<thumbnail>https://i.postimg.cc/y6pC45gC/tmpposter20564.jpg</thumbnail>
<fanart></fanart>
</item>

<item>
<title>Vanguard (2020) [COLORblue]7.5-Action/Eng.Subs[/COLOR]</title>
<link>https://mixdrop.co/f/0v30v1wkhdjpg4</link>
<thumbnail>https://i.postimg.cc/pXdVKz8R/tmpposter27265.jpg</thumbnail>
<fanart></fanart>
</item>

<item>
<title>Pinocchio (2019) [COLORblue]Fantasy/Family/Adventure/Drama[/COLOR]</title>
<link>https://mixdrop.co/f/4ndwrmgosddlvq</link>
<thumbnail>https://i.postimg.cc/FFnCQnv0/4w1-Itw-CJCTt-Si9n-Pf-JC1v-U6-NIVg.jpg</thumbnail>
<fanart></fanart>
</item>

<item>
<title>Jiu Jitsu (2020) [COLORblue]Action/Sci-Fi[/COLOR]</title>
<link>https://aparat.cam/pdqli9mym03r</link>
<thumbnail>https://i.postimg.cc/BvvhPMw0/poster-opt.jpg</thumbnail>
<fanart></fanart>
</item>

<item>
<title>Faith Under Fire (2020) [COLORblue]Drama[/COLOR]</title>
<link>https://aparat.cam/fgcz8ssq6787</link>
<thumbnail>https://i.postimg.cc/J4QTHBq1/tmpposter24173.jpg</thumbnail>
<fanart></fanart>
</item>

<item>
<title>Bobbleheads: The Movie (2020) [COLORblue]Animation/Family[/COLOR]</title>
<link>https://aparat.cam/drixpbap1mja</link>
<thumbnail>https://i.postimg.cc/QtVmqS3k/tmpposter13985.jpg</thumbnail>
<fanart></fanart>
</item>

<item>
<title>Knuckledust (2020) [COLORblue]Action/Thriller[/COLOR]</title>
<link>https://aparat.cam/rzxth5zu00jb</link>
<thumbnail>https://i.postimg.cc/65G6FV5Y/tmpposter8183.jpg</thumbnail>
<fanart></fanart>
</item>

<item>
<title>The Last Champion (2019) [COLORblue]Drama/Family/Sport[/COLOR]</title>
<link>https://aparat.cam/8ay2dzlvluvy</link>
<thumbnail>https://i.postimg.cc/BZPFzT2v/y4m9ho-Zo-U8.jpg</thumbnail>
<fanart></fanart>
</item>

<item>
<title>The Rizen: Possession (2019) [COLORblue]4.9-Action/Horror/Sci-Fi[/COLOR]</title>
<link>https://mixdrop.co/f/7rkex1vecdwdvrn</link>
<thumbnail>https://i.postimg.cc/pdBhDkN0/tmpposter22700.jpg</thumbnail>
<fanart></fanart>
</item>

<item>
<title>Sexual Animals (2019) [COLORblue]Comedy[/COLOR]</title>
<link>https://mixdrop.co/f/3n6elkg0u3q89r</link>
<thumbnail>https://i.postimg.cc/1XvfLzRD/l8ox-ZBWys1.jpg</thumbnail>
<fanart></fanart>
</item>

<item>
<title>Shedding (2019) [COLORblue]8.1-Drama/Fantasy[/COLOR]</title>
<link>https://mixdrop.co/f/4ndewlwgbqkzez8</link>
<thumbnail>https://i.postimg.cc/2Sz0QcMJ/444z-Nij-IWO.jpg</thumbnail>
<fanart></fanart>
</item>

<item>
<title>Monsters of Man (2020) [COLORblue]Sci-Fi[/COLOR]</title>
<link>https://aparat.cam/6r05iu37h912</link>
<thumbnail>https://i.postimg.cc/85CFwD49/tmpposter30816.jpg</thumbnail>
<fanart></fanart>
</item>

<item>
<title>The Planters (2019) [COLORblue]7.3-Comedy[/COLOR]</title>
<link>https://mixdrop.co/f/enlv3qdntqwel1</link>
<thumbnail>https://i.postimg.cc/8z3nTPJB/tmpposter13243.jpg</thumbnail>
<fanart></fanart>
</item>

<item>
<title>Sarah Q (2018) [COLORblue]6.5-Comedy/Drama[/COLOR]</title>
<link>https://mixdrop.co/f/9nweevr9s6k9e6</link>
<thumbnail>https://i.postimg.cc/4yYQ1K1Y/tmpposter5104.jpg</thumbnail>
<fanart></fanart>
</item>

<item>
<title>HUMANUS (2020)</title>
<link>https://mixdrop.co/f/gnjrrepwuwjreg</link>
<thumbnail>https://i.postimg.cc/pX9sfS0s/m2-Zup-NNz-TK.jpg</thumbnail>
<fanart></fanart>
</item>

<item>
<title>Black Pumpkin (2018) [COLORblue]6.0-Horror[/COLOR]</title>
<link>https://streamtape.com/v/Ma7b9jk6d6Hm7Rj</link>
<thumbnail>https://i.postimg.cc/qq4cWB2G/w-Oy-YZN4sek.jpg</thumbnail>
<fanart></fanart>
</item>

<item>
<title>Quest of the Muscle Nerd (2019) [COLORblue]7.5-Docu.[/COLOR]</title>
<link>https://aparat.cam/y7ju2whziufv</link>
<thumbnail>https://i.postimg.cc/vmLNDmJs/poster-opt.jpg</thumbnail>
<fanart></fanart>
</item>

<item>
<title>Keith Haring: Street Art Boy (2020) [COLORblue]7.4-Bio./Docu.[/COLOR]</title>
<link>https://aparat.cam/7jldzr5j1xg3</link>
<thumbnail>https://i.postimg.cc/FKNGTWV4/poster-opt.jpg</thumbnail>
<fanart></fanart>
</item>

<item>
<title>Time Loop (2020) [COLORblue]3.5-Adventure/Sci-Fi/Makes No Sense[/COLOR]</title>
<link>https://aparat.cam/46vaifopvef8</link>
<thumbnail>https://i.postimg.cc/Z5hCtrdj/poster-opt.jpg</thumbnail>
<fanart></fanart>
</item>

<item>
<title>Love Dave (2020) [COLORblue]6.1-Drama/Thriller[/COLOR]</title>
<link>https://aparat.cam/561uxcgtm9bn</link>
<thumbnail>https://i.postimg.cc/tC5bsMDV/tmpposter14773.jpg</thumbnail>
<fanart></fanart>
</item>

<item>
<title>My Day (2019) [COLORblue]Drama[/COLOR]</title>
<link>https://aparat.cam/r88qtijzmai0</link>
<thumbnail>https://i.postimg.cc/855NGBLr/Tx0ek7t-JLp.jpg</thumbnail>
<fanart></fanart>
</item>

<item>
<title>Magic Arch (2020) [COLORblue]6.0-Animation/Family[/COLOR]</title>
<link>https://aparat.cam/hgjwxszp6lxg</link>
<thumbnail>https://i.postimg.cc/4dTVFycM/tmpposter3778.jpg</thumbnail>
<fanart></fanart>
</item>

<item>
<title>The Fairy Princess and the Unicorn (2020) [COLORblue]5.4-Animation/Adventure/Family/Fantasy[/COLOR]</title>
<link>https://mixdrop.co/f/l670lj94aleog</link>
<thumbnail>https://i.postimg.cc/9fkN4Gv9/tmpposter28407.jpg</thumbnail>
<fanart></fanart>
</item>

<item>
<title>Spare Parts (2020) [COLORblue]5.4-Horror[/COLOR]</title>
<link>https://streamtape.com/v/PGYQyLqK1bh0Z4y</link>
<thumbnail>https://i.postimg.cc/vTgqLcwK/tmpposter2849.jpg</thumbnail>
<fanart></fanart>
</item>

<item>
<title>Greenland (2020) [COLORblue]6.3-Action/Drama/Thriller[/COLOR]</title>
<link>https://aparat.cam/h9428htqu86l</link>
<thumbnail>https://i.postimg.cc/RFCgQ9PQ/poster-opt.jpg</thumbnail>
<fanart></fanart>
</item>

<item>
<title>Hoax (2019) [COLORblue]3.9-Horror[/COLOR]</title>
<link>https://aparat.cam/u56fabv9mg0q/Hoax.2019.1080p.BluRay.H264.AAC-RARBG.mp4.html</link>
<thumbnail>https://dyncdn.me/mimages/341767/poster_opt.jpg</thumbnail>
<fanart></fanart>
</item>

<item>
<title>High Ground (2020) [COLORblue]6.2-Action/Thriller[/COLOR]</title>
<link>https://aparat.cam/jr41w8zfv1va/High.Ground.2020.1080p.BluRay.H264.AAC-RARBG.mp4.html</link>
<thumbnail>https://dyncdn.me/mimages/354087/poster_opt.jpg</thumbnail>
<fanart></fanart>
</item>

<item>
<title>Honest Thief (2020) [COLORblue]6.5-Action/Crime/Drama/Thriller[/COLOR]</title>
<link>https://aparat.cam/p94x5sfbk9vi</link>
<thumbnail>https://imgmak.com/images/2020/12/05/tmpposter22498.jpg</thumbnail>
<fanart></fanart>
</item>

<item>
<title>Zombie Bro (2019) [COLORblue]Comedy/Family/Fantasy[/COLOR]</title>
<link>https://clicknupload.co/taclsgp9hc0z</link>
<thumbnail>https://imgmak.com/images/2020/12/04/tmpposter4949.jpg</thumbnail>
<fanart></fanart>
</item>

<item>
<title>No Place (2020) [COLORblue]Crime-80 mins[/COLOR]</title>
<link>https://aparat.cam/mxff6o9cq0xr/No.Place.2020.1080p.WEBRip.x264-RARBG.mp4.html</link>
<thumbnail>https://img.picturegalaxy.org/data/cover/imdb/V/a/Va42hlhGWK.jpg</thumbnail>
<fanart></fanart>
</item>

<item>
<title>Survival Skills (2020) [COLORblue]6.7-Comedy/Drama[/COLOR]</title>
<link>https://aparat.cam/r5jymhf7joqa/Survival.Skills.2020.1080p.WEBRip.x264-RARBG.mp4.html</link>
<thumbnail>https://dyncdn.me/mimages/354078/poster_opt.jpg</thumbnail>
<fanart></fanart>
</item>

<item>
<title>Castle Freak (2020) [COLORblue]6.2-Horror[/COLOR]</title>
<link>https://aparat.cam/lrpwlndn4y5b/Castle.Freak.2020.1080p.WEBRip.x264-RARBG.mp4.html</link>
<thumbnail>https://dyncdn.me/mimages/354061/poster_opt.jpg</thumbnail>
<fanart></fanart>
</item>

<item>
<title>Godmothered (2020) [COLORblue]Comedy/Fantasy[/COLOR]</title>
<link>https://aparat.cam/myjfa0xto4fe/Godmothered.2020.1080p.WEBRip.x264-RARBG.mp4.html</link>
<thumbnail>https://imgmak.com/images/2020/12/04/tmpposter13945.jpg</thumbnail>
<fanart></fanart>
</item>

<item>
<title>What Lies Below (2020) [COLORblue]Mystery/Thriller[/COLOR]</title>
<link>https://aparat.cam/egfkmpx5l4hc/What.Lies.Below.2020.1080p.WEBRip.x264-RARBG.mp4.html</link>
<thumbnail>https://imgmak.com/images/2020/12/04/tmpposter21259.jpg</thumbnail>
<fanart></fanart>
</item>

<item>
<title>Black Bear (2020) [COLORblue]7.1-Drama[/COLOR]</title>
<link>https://aparat.cam/0dargqs0g4vc/Black.Bear.2020.1080p.WEBRip.x264-RARBG.mp4.html</link>
<thumbnail>https://imgmak.com/images/2020/12/04/tmpposter6114.jpg</thumbnail>
<fanart></fanart>
</item>

<item>
<title>Mank (2020) *[COLORblue]7.9-Biography/Comedy/Drama[/COLOR]</title>
<link>https://aparat.cam/gwxizt8cm7j8/Mank.2020.1080p.WEBRip.x264-RARBG.mp4.html</link>
<thumbnail>https://imgmak.com/images/2020/12/04/tmpposter32378.jpg</thumbnail>
<fanart></fanart>
</item>

<item>
<title>Wander (2020) [COLORblue]7.7-Thriller[/COLOR]</title>
<link>https://streamtape.com/v/ayar4WXOb8Ux4pk</link>
<thumbnail>https://i.postimg.cc/RZ9pVccD/tmpposter22698.jpg</thumbnail>
<fanart></fanart>
</item>

<item>
<title>Minor Premise (2020) [COLORblue]6.8-Drama/Sci-Fi/Thriller[/COLOR]</title>
<link>https://mixdrop.co/f/wnl73zm7tnj71r</link>
<thumbnail>https://imgmak.com/images/2020/12/04/tmpposter30203.jpg</thumbnail>
<fanart></fanart>
</item>

<item>
<title>Elyse (2020) [COLORblue]Drama[/COLOR]</title>
<link>https://mixdrop.co/f/kn0zd4p3c861m0</link>
<thumbnail>https://imgmak.com/images/2020/12/04/tmpposter14718.jpg</thumbnail>
<fanart></fanart>
</item>

<item>
<title>Sound of Metal (2019) [COLORblue]7.3-Drama/Music[/COLOR]</title>
<link>https://aparat.cam/d06pon1cottm/Sound.of.Metal.2019.1080p.WEBRip.x264-RARBG.mp4.html</link>
<thumbnail>https://imgmak.com/images/2020/12/04/tmpposter9922.jpg</thumbnail>
<fanart></fanart>
</item>

<item>
<title>Muscle (2019) [COLORblue]7.0-Thriller[/COLOR]</title>
<link>https://mixdrop.co/f/6q788qqwsll94w9</link>
<thumbnail>https://imgmak.com/images/2020/12/04/tmpposter9200.jpg</thumbnail>
<fanart></fanart>
</item>

<item>
<title>Tenet (2020) (1080p) IMAX [COLORblue]7.8-Action/Drama/Thriller[/COLOR]</title>
<link>https://aparat.cam/n45wm6r0cllr/Tenet.2020.IMAX.1080p.BluRay.H264.AAC-RARBG.mp4.html</link>
<thumbnail>https://i.imgur.com/ggz0mNl.jpg</thumbnail>
<fanart></fanart>
</item>

<item>
<title>Tenet (2020) (720p) IMAX [COLORblue]7.8-Action/Drama/Thriller[/COLOR]</title>
<link>https://aparat.cam/mdgbk3fgkdp8/Tenet.2020.IMAX.720p.BluRay.H264.AAC-RARBG.mp4.html</link>
<thumbnail>https://i.imgur.com/ggz0mNl.jpg</thumbnail>
<fanart></fanart>
</item>

<item>
<title>Tenet (2020) (720p) IMAX [COLORblue]7.8-Action/Drama/Thriller[/COLOR]</title>
<link>https://mixdrop.co/f/j9dxxqrgt16dq3</link>
<thumbnail>https://i.imgur.com/ggz0mNl.jpg</thumbnail>
<fanart></fanart>
</item>

<item>
<title>Free Lunch Express (2020) [COLORblue]Comedy[/COLOR]</title>
<link>https://aparat.cam/2jxwckd22pm4/Free.Lunch.Express.2020.1080p.WEBRip.x264-RARBG.mp4.html</link>
<thumbnail>https://i.imgur.com/IJtZ41c.jpg</thumbnail>
<fanart></fanart>
</item>

<item>
<title>Ammonite (2020) [COLORblue]6.4-Biography/Drama/Romance[/COLOR]</title>
<link>https://streamtape.com/v/jvXr7RVwP9szWb9</link>
<thumbnail>https://i.imgur.com/PYZC7W9.jpg</thumbnail>
<fanart></fanart>
</item>

<item>
<title>Freaky (2020) (1080p) [COLORblue]6.8-Comedy/Horror/Thriller[/COLOR]</title>
<link>https://aparat.cam/n3e9dmutgop9/Freaky.2020.1080p.WEBRip.x264-RARBG.mp4.html</link>
<thumbnail>https://i.imgur.com/VAEJ5R3.jpg</thumbnail>
<fanart></fanart>
</item>

<item>
<title>Freaky (2020) (1080p) [COLORblue]6.8-Comedy/Horror/Thriller[/COLOR]</title>
<link>https://streamtape.com/v/01Rozp4ZGAUblJL</link>
<thumbnail>https://i.imgur.com/VAEJ5R3.jpg</thumbnail>
<fanart></fanart>
</item>

<item>
<title>Freaky (2020) (720p) [COLORblue]6.8-Comedy/Horror/Thriller[/COLOR]</title>
<link>https://clicknupload.co/hx3tmhjwfwch</link>
<thumbnail>https://i.imgur.com/VAEJ5R3.jpg</thumbnail>
<fanart></fanart>
</item>

<item>
<title>Anything for Jackson (2020) [COLORblue]7.3-Horror[/COLOR]</title>
<link>https://mixdrop.co/f/1vnx0jx7ukk3q0v</link>
<thumbnail>https://i.imgur.com/pm2ChEV.jpg</thumbnail>
<fanart></fanart>
</item>

<item>
<title>The Legend of Baron To'a (2020) [COLORblue]7.2-Action/Comedy[/COLOR]</title>
<link>https://mixdrop.co/f/0v31wwx4hklxzkq</link>
<thumbnail>https://i.imgur.com/ZE8feMJ.jpg</thumbnail>
<fanart></fanart>
</item>

<item>
<title>Baby God (2020) [COLORblue]Docu.[/COLOR]</title>
<link>https://mixdrop.co/f/dqk7w3qgtqdpne</link>
<thumbnail>https://i.imgur.com/5dgoNNu.jpg</thumbnail>
<fanart></fanart>
</item>

<item>
<title>Christmas Together (2020) [COLORblue]Crimbo[/COLOR]</title>
<link>https://mixdrop.co/f/9nwr89ldsqdm8k</link>
<thumbnail>https://i.imgur.com/EEJMxVB.jpg</thumbnail>
<fanart></fanart>
</item>

<item>
<title>The Truth About Amazon How Took Over the World (2020) [COLORblue]Docu.[/COLOR]</title>
<link>https://streamtape.com/v/J61AQBpeMXhjK2R</link>
<thumbnail>https://i.imgur.com/ogv2jxP.jpeg</thumbnail>
<fanart></fanart>
</item>

<item>
<title>The Haunting of Margam Castle (2020) [COLORblue]Horror[/COLOR]</title>
<link>https://aparat.cam/xil80r31cvth/The.Haunting.of.Margam.Castle.2020.1080p.WEBRip.x264-RARBG.mp4.html</link>
<thumbnail>https://i.imgur.com/e7Lbv9b.jpg</thumbnail>
<fanart></fanart>
</item>

<item>
<title>Checkmate (2019) [COLORblue]Thriller[/COLOR]</title>
<link>https://aparat.cam/rwa9k4b019fa/Checkmate.2019.PROPER.1080p.WEBRip.x264-RARBG.mp4.html</link>
<thumbnail>https://i.imgur.com/ZRzST5o.jpg</thumbnail>
<fanart></fanart>
</item>

<item>
<title>Ellie & Abbie (& Ellie's Dead Aunt) (2020) [COLORblue]7.9-Comedy[/COLOR]</title>
<link>https://streamtape.com/v/W9vL979qoMubBeD</link>
<thumbnail>https://imgmak.com/images/2020/12/01/tmpposter1030.jpg</thumbnail>
<fanart></fanart>
</item>

<item>
<title>Angela's Christmas Wish (2020) [COLORblue]5.2-Animation/Adventure/Family[/COLOR]</title>
<link>https://streamtape.com/v/g1ZZrW3pXeSq2Yg</link>
<thumbnail>https://i.imgur.com/6arnR1s.jpg</thumbnail>
<fanart></fanart>
</item>

<item>
<title>Trail of Ashes (2020) [COLORblue]9.3-Fantasy/Mystery[/COLOR]</title>
<link>https://streamtape.com/v/zQmJD4qqZ7HYjbJ</link>
<thumbnail>https://i.imgur.com/XMOleQH.jpg</thumbnail>
<fanart></fanart>
</item>

<item>
<title>Santa's Promise (2020) [COLORblue]Crimbo[/COLOR]</title>
<link>https://mixdrop.co/f/o7w8xqxku3d6lq</link>
<thumbnail>https://i.imgur.com/6FT2fZC.jpg</thumbnail>
<fanart></fanart>
</item>

<item>
<title>Break Even (2020) [COLORblue]Action[/COLOR]</title>
<link>https://aparat.cam/89a5adyv2z3d/Break.Even.2020.1080p.WEBRip.x264-RARBG.mp4.html</link>
<thumbnail>https://i.imgur.com/PtIokUF.jpg</thumbnail>
<fanart></fanart>
</item>

<item>
<title>Onus (2020) [COLORblue]Horror[/COLOR]</title>
<link>https://mixdrop.co/f/84lnorlgt1nzwn</link>
<thumbnail>https://i.imgur.com/KsOIDk7.jpg</thumbnail>
<fanart></fanart>
</item>

<item>
<title>Esau (2019) [COLORblue]5.1-Drama[/COLOR]</title>
<link>https://mixdrop.co/f/7rkvqw00fq8ppw</link>
<thumbnail>https://i.imgur.com/bGCtGeO.jpg</thumbnail>
<fanart></fanart>
</item>

<item>
<title>Beast Mode (2020) [COLORblue]7.1-Horror[/COLOR]</title>
<link>https://aparat.cam/gg12l8whu1yb/Beast.Mode.2020.1080p.WEBRip.x264-RARBG.mp4.html</link>
<thumbnail>https://i.imgur.com/FiGFNGX.jpg</thumbnail>
<fanart></fanart>
</item>

<item>
<title>First Lady (2020) [COLORblue]5.4-Comedy/Romance[/COLOR]</title>
<link>https://aparat.cam/nrls9bmpnwkn/First.Lady.2020.1080p.WEBRip.x264-RARBG.mp4.html</link>
<thumbnail>https://i.imgur.com/VdgSZ7U.jpg</thumbnail>
<fanart></fanart>
</item>

<item>
<title>Deadlocked (2021) [COLORblue]Horror/Thriller[/COLOR]</title>
<link>https://aparat.cam/2i5n4zlz59rk/Deadlocked.2021.1080p.WEBRip.x264-RARBG.mp4.html</link>
<thumbnail>https://i.imgur.com/vtVeZtn.jpg</thumbnail>
<fanart></fanart>
</item>

<item>
<title>Dreamfactory (2019) [COLORblue]6.5-Comedy/Drama/Romance[/COLOR]</title>
<link>https://mixdrop.co/f/vnk09qjrcgj671</link>
<thumbnail>https://i.imgur.com/S9FO0kN.jpg</thumbnail>
<fanart></fanart>
</item>

<item>
<title>Intersection (2020) [COLORblue]Thriller[/COLOR]</title>
<link>https://aparat.cam/cfifa1947brm/Intersection.2020.1080p.WEBRip.x264-RARBG.mp4.html</link>
<thumbnail>https://i.imgur.com/C7m3psV.jpg</thumbnail>
<fanart></fanart>
</item>

<item>
<title>Occurrence at Mills Creek (2020) [COLORblue]7.5-Drama/Horror[/COLOR]</title>
<link>https://aparat.cam/n47ltvyt3mb9/Occurrence.at.Mills.Creek.2020.1080p.WEBRip.x264-RARBG.mp4.html</link>
<thumbnail>https://i.imgur.com/xGX55hI.jpg</thumbnail>
<fanart></fanart>
</item>

<item>
<title>King of Knives (2020) [COLORblue]Comedy/Drama[/COLOR]</title>
<link>https://aparat.cam/kob9v9kp7njj/King.of.Knives.2020.1080p.WEBRip.x264-RARBG.mp4.html</link>
<thumbnail>https://i.imgur.com/HyHfD5c.jpg</thumbnail>
<fanart></fanart>
</item>

<item>
<title>Dune Drifter (2020) [COLORblue]6.7-Sci-Fi[/COLOR]</title>
<link>https://aparat.cam/u106prjactl5/Dune.Drifter.2020.1080p.WEBRip.x264-RARBG.mp4.html</link>
<thumbnail>https://i.imgur.com/JbCJlxp.jpg</thumbnail>
<fanart></fanart>
</item>

<item>
<title>Infidel (2019) [COLORblue]6.7-Action/Adventure/Thriller[/COLOR]</title>
<link>https://aparat.cam/dx3tvv9oknv8/Infidel.2019.1080p.WEBRip.x264-RARBG.mp4.html</link>
<thumbnail>https://i.imgur.com/FtHfWm5.jpg</thumbnail>
<fanart></fanart>
</item>

<item>
<title>Legacy of Lies (2020) [COLORblue]4.9-Action/Thriller[/COLOR]</title>
<link>https://aparat.cam/xrwu04xxgucq/Legacy.of.Lies.2020.1080p.BluRay.H264.AAC-RARBG.mp4.html</link>
<thumbnail>https://i.imgur.com/CwTuyZr.jpg</thumbnail>
<fanart></fanart>
</item>

<item>
<title>Complete Strangers (2020) [COLORblue]Drama/Thriller[/COLOR]</title>
<link>https://mixdrop.co/f/n0lq8rzefj9ggp</link>
<thumbnail>https://i.imgur.com/mcYa28a.jpg</thumbnail>
<fanart></fanart>
</item>

<item>
<title>18 to Party (2019) [COLORblue]5.4-Comedy[/COLOR]</title>
<link>https://aparat.cam/y3h1dwk2m8um/18.To.Party.2019.1080p.WEBRip.x264.AAC5.1-[YTS.MX].mp4.html</link>
<thumbnail>https://i.imgur.com/JDbpv5S.jpg</thumbnail>
<fanart></fanart>
</item>

<item>
<title>Completely Unrehearsed Last Minute Pandemic Holiday Special (2020)</title>
<link>https://aparat.cam/x8hmaz1uio8i/Completely.Unrehearsed.Last.Minute.Pandemic.Holiday.Special.2020.1080p.WEBRip.x264.AAC-[YTS.MX].mp4.html</link>
<thumbnail>https://i.imgur.com/Uunkwlk.jpg</thumbnail>
<fanart></fanart>
</item>

<item>
<title>The Taverna (2019) [COLORblue]7.1-Comedy[/COLOR]</title>
<link>https://mixdrop.co/f/enlp39vriq6w13</link>
<thumbnail>https://i.imgur.com/oEuS6Cg.jpg</thumbnail>
<fanart></fanart>
</item>

<item>
<title>The Donut King (2020) [COLORblue]8.1-Docu.[/COLOR]</title>
<link>https://aparat.cam/bknfglni7mpi/The.Donut.King.2020.1080p.WEBRip.x264-RARBG.mp4.html</link>
<thumbnail>https://i.imgur.com/T5rVyEl.jpg</thumbnail>
<fanart></fanart>
</item>

<item>
<title>Zappa (2020) [COLORblue]7.9-Docu.[/COLOR]</title>
<link>https://dood.to/d/1q66dsvgh6jc</link>
<thumbnail>https://i.imgur.com/qGosBwD.jpg</thumbnail>
<fanart></fanart>
</item>

<item>
<title>Antarctica (2020) [COLORblue]8.4-Comedy/Romance[/COLOR]</title>
<link>https://mixdrop.co/f/1vnrrgvrbkr08r</link>
<thumbnail>https://i.imgur.com/ehsLypI.jpg</thumbnail>
<fanart></fanart>
</item>

<item>
<title>The Knight and the Princess (2019) [COLORblue]7.9-Animation/Adventure/Comedy/Family/History/Musical[/COLOR]</title>
<link>https://mixdrop.co/f/4nd0041dfqlk0rq</link>
<thumbnail>https://i.imgur.com/kGuGA8g.jpg</thumbnail>
<fanart></fanart>
</item>

<item>
<title>A Night in 97 (2020) [COLORblue]Thriller[/COLOR]</title>
<link>https://mixdrop.co/f/3n6ddrn3bmw7o9l</link>
<thumbnail>https://i.imgur.com/pVngqz6.jpg</thumbnail>
<fanart></fanart>
</item>

<item>
<title>The Loss Adjuster (2020) [COLORblue]6.5-Comedy/Drama[/COLOR]</title>
<link>https://mixdrop.co/f/6q7kk7glfzggpx</link>
<thumbnail>https://i.imgur.com/UkrSCQh.jpg</thumbnail>
<fanart></fanart>
</item>

<item>
<title>The Loss Adjuster (2020) [COLORblue]6.5-Comedy/Drama[/COLOR]</title>
<link>https://www.fembed.com/v/08jwpil-wk8r5nn</link>
<thumbnail>https://i.imgur.com/UkrSCQh.jpg</thumbnail>
<fanart></fanart>
</item>

<item>
<title>Cordelia (2019) [COLORblue]6.7-Drama/Horror/Thriller[/COLOR]</title>
<link>https://streamtape.com/v/Alko0yaZBBiXld9</link>
<thumbnail>https://i.imgur.com/9vYCpoQ.jpg</thumbnail>
<fanart></fanart>
</item>

<item>
<title>A Taste of Christmas (2020) [COLORblue]Crimbo[/COLOR]</title>
<link>https://mixdrop.co/f/zp16lkknfnvn94</link>
<thumbnail>https://i.imgur.com/7sybtst.jpg</thumbnail>
<fanart></fanart>
</item>

<item>
<title>Dear Christmas (2020) [COLORblue]Crimbo[/COLOR]</title>
<link>https://mixdrop.co/f/ql1xz8m4bo11ve</link>
<thumbnail>https://i.imgur.com/V3v7T2m.jpg</thumbnail>
<fanart></fanart>
</item>

<item>
<title>Minions Holiday Special (2020) [COLORblue]Animation/Family[/COLOR]</title>
<link>https://mixdrop.co/f/84lw84mvcnkqm6</link>
<thumbnail>https://i.imgur.com/NpvsLMN.jpg</thumbnail>
<fanart></fanart>
</item>

<item>
<title>Kevin Hart: Zero F**ks Given (5.1) (2020) [COLORblue]6.0-Action/Comedy[/COLOR]</title>
<link>https://aparat.cam/upl4rnn1hhpe/Kevin.Hart.Zero.F.ks.Given.2020.1080p.BluRay.x264.AAC5.1-[YTS.MX].mp4.html</link>
<thumbnail>https://i.imgur.com/TnLgnH7.jpg</thumbnail>
<fanart></fanart>
</item>

<item>
<title>After We Collided (5.1) (2020) [COLORblue]5.1-Drama/Romance[/COLOR]</title>
<link>https://aparat.cam/tj5mrqpadu4h/After.We.Collided.2020.1080p.BluRay.x264.AAC5.1-[YTS.MX].mp4.html</link>
<thumbnail>https://i.imgur.com/O0TnZaj.jpg</thumbnail>
<fanart></fanart>
</item>

<item>
<title>Riding with Sugar (5.1) (2020) [COLORblue]Drama[/COLOR]</title>
<link>https://aparat.cam/vz33y5g7r9mn/Riding.With.Sugar.2020.1080p.WEBRip.x264-RARBG.mp4.html</link>
<thumbnail>https://i.imgur.com/Vz9f6VM.jpg</thumbnail>
<fanart></fanart>
</item>

<item>
<title>Tenet (2020) 1080p [COLORblue]7.8-Action/Drama/Thriller[/COLOR]</title>
<link>https://streamtape.com/v/KzV08olvm2iogk</link>
<thumbnail>https://i.imgur.com/ggz0mNl.jpg</thumbnail>
<fanart></fanart>
</item>

<item>
<title>Tenet (2020) 1080p [COLORblue]7.8-Action/Drama/Thriller[/COLOR]</title>
<link>https://clicknupload.co/j3u6oq8bdbt3</link>
<thumbnail>https://i.imgur.com/ggz0mNl.jpg</thumbnail>
<fanart></fanart>
</item>

<item>
<title>Tenet (2020) 720p [COLORblue]7.8-Action/Drama/Thriller[/COLOR]</title>
<link>https://clicknupload.co/tp564h1jywk6</link>
<thumbnail>https://i.imgur.com/ggz0mNl.jpg</thumbnail>
<fanart></fanart>
</item>

<item>
<title>Life in a Year (5.1) (2020) [COLORblue]5.2-Drama/Romance[/COLOR]</title>
<link>https://aparat.cam/1k97ofjlm4qa/Life.in.a.Year.2020.1080p.WEBRip.x264-RARBG.mp4.html</link>
<thumbnail>https://i.imgur.com/WX23c4d.jpg</thumbnail>
<fanart></fanart>
</item>

<item>
<title>Black Beauty (5.1) (2020) [COLORblue]Drama/Family[/COLOR]</title>
<link>https://aparat.cam/509qv0jqbwv6/Black.Beauty.2020.1080p.WEBRip.x264.AAC5.1-[YTS.MX].mp4.html</link>
<thumbnail>https://i.imgur.com/5yXwEt2.jpg</thumbnail>
<fanart></fanart>
</item>

<item>
<title>The Class Of '92 (2013)</title>
<link>https://streamtape.com/v/BYa7qdOkJZFyd87</link>
<thumbnail>https://i.imgur.com/SsKDte5.jpg</thumbnail>
<fanart></fanart>
</item>

<item>
<title>The Vigil (2019) [COLORblue]5.8-Horror/Mystery/Thriller[/COLOR]</title>
<link>https://mixdrop.co/f/gnjpmlznslzreo</link>
<thumbnail>https://i.imgur.com/w1XT4OF.jpg</thumbnail>
<fanart></fanart>
</item>

<item>
<title>Faith (5.1) (2019) [COLORblue]Drama[/COLOR]</title>
<link>https://aparat.cam/pg9cv1u1mrbv/Faith.2019.1080p.WEBRip.x264-RARBG.mp4.html</link>
<thumbnail>https://i.imgur.com/dNWsbtO.jpg</thumbnail>
<fanart></fanart>
</item>

<item>
<title>Midnight at the Magnolia (5.1) (2020) [COLORblue]6.1-Comedy/Romance[/COLOR]</title>
<link>https://aparat.cam/b1tzbkly53ek/Midnight.at.the.Magnolia.2020.1080p.WEBRip.x264-RARBG.mp4.html</link>
<thumbnail>https://i.imgur.com/zq8COgd.jpg</thumbnail>
<fanart></fanart>
</item>

<item>
<title>Princess of the Row (2019) [COLORblue]7.2-Drama[/COLOR]</title>
<link>https://mixdrop.co/f/vnk8197pb0v1qg</link>
<thumbnail>https://i.imgur.com/CfWczYz.jpg</thumbnail>
<fanart></fanart>
</item>

<item>
<title>A Christmas Break (2020) [COLORblue]Christmas[/COLOR]</title>
<link>https://aparat.cam/ctm4fvovaqjs/A.Christmas.Break.2020.1080p.WEBRip.x264-RARBG.mp4.html</link>
<thumbnail>https://i.imgur.com/4kYTS3G.jpg</thumbnail>
<fanart></fanart>
</item>

<item>
<title>The Santa Squad (2020) [COLORblue]Christmas[/COLOR]</title>
<link>https://aparat.cam/unl71e7v669j/The.Santa.Squad.2020.1080p.WEBRip.x264-RARBG.mp4.html</link>
<thumbnail>https://i.imgur.com/fUO8gW5.jpg</thumbnail>
<fanart></fanart>
</item>

<item>
<title>Superintelligence (5.1) (2020) [COLORblue]4.4-Action/Comedy[/COLOR]</title>
<link>https://aparat.cam/7lb3d6diabs9/Superintelligence.2020.1080p.WEBRip.x264-RARBG.mp4.html</link>
<thumbnail>https://i.imgur.com/fbRIpCp.jpg</thumbnail>
<fanart></fanart>
</item>

<item>
<title>The Killing of John Lennon (5.1) (2006) [COLORblue]6.3-Crime/Drama[/COLOR]</title>
<link>https://aparat.cam/azt36pc64h3w/The.Killing.Of.John.Lennon.2006.1080p.WEBRip.x264-RARBG.mp4.html</link>
<thumbnail>https://i.imgur.com/Iqd6NGK.jpg</thumbnail>
<fanart></fanart>
</item>

<item>
<title>Made in Italy (5.1) (2020) [COLORblue]5.7-Comedy[/COLOR]</title>
<link>https://aparat.cam/8s0mgqgsy24y/Made.In.Italy.2020.1080p.BluRay.x264.AAC5.1-[YTS.MX].mp4.html</link>
<thumbnail>https://i.imgur.com/zhkZ4G3.jpg</thumbnail>
<fanart></fanart>
</item>

<item>
<title>Dragons: Rescue Riders: Huttsgalor Holiday (5.1) (2020) [COLORblue]7.0-Family[/COLOR]</title>
<link>https://aparat.cam/srv7tn2f0bx9/Dragons.Rescue.Riders.Huttsgalor.Holiday.2020.1080p.WEBRip.x264-RARBG.mp4.html</link>
<thumbnail>https://i.imgur.com/pwkoBT7.jpg</thumbnail>
<fanart></fanart>
</item>

<item>
<title>The Christmas Chronicles: Part Two (5.1) (2020) [COLORblue]Adventure/Comedy/Family/Fantasy[/COLOR]</title>
<link>https://aparat.cam/fqerh66llcic/The.Christmas.Chronicles.2.2020.1080p.WEBRip.x264-RARBG.mp4.html</link>
<thumbnail>https://i.imgur.com/JPMgCgo.jpg</thumbnail>
<fanart></fanart>
</item>

<dir>
<title>[COLOR lime]>>> New Releases Next Page If You're Using Maverick >>>[/COLOR]</title>
<link>https://raw.githubusercontent.com/Floyd6969/DJV/master/RecentRelsFree</link>
<thumbnail>https://i.imgur.com/r6nMlcQ.png</thumbnail>
<fanart></fanart>
</dir>
 
<item>
<title>[COLOR gold]>>> New Releases Next Page If You're Using DejaVu[/COLOR] [COLOR red]Or Free>>>[/COLOR]</title>
<link>https://raw.githubusercontent.com/Floyd6969/DJV/master/RecentRelsFree</link>
<externallink>https://raw.githubusercontent.com/Floyd6969/DJV/master/RecentRelsFree</externallink>
<thumbnail>https://i.imgur.com/r6nMlcQ.png</thumbnail>
<fanart></fanart>
</item>
