<item>
<title>Truth Seekers S01 E01</title>
<link>https://clicknupload.co/fchi7yycs14b</link>
<thumbnail>https://i.imgur.com/ZCJA73Y.jpg</thumbnail>
<fanart></fanart>
</item>

<item>
<title>Truth Seekers S01 E02</title>
<link>https://clicknupload.co/r98we4oe8hc6</link>
<thumbnail>https://i.imgur.com/ZCJA73Y.jpg</thumbnail>
<fanart></fanart>
</item>

<item>
<title>Truth Seekers S01 E03</title>
<link>https://clicknupload.co/ttxlmerwueyb</link>
<thumbnail>https://i.imgur.com/ZCJA73Y.jpg</thumbnail>
<fanart></fanart>
</item>

<item>
<title>Truth Seekers S01 E04</title>
<link>https://clicknupload.co/ozomi76snvf0</link>
<thumbnail>https://i.imgur.com/ZCJA73Y.jpg</thumbnail>
<fanart></fanart>
</item>

<item>
<title>Truth Seekers S01 E05</title>
<link>https://clicknupload.co/opt4ke6p9x13</link>
<thumbnail>https://i.imgur.com/ZCJA73Y.jpg</thumbnail>
<fanart></fanart>
</item>

<item>
<title>Truth Seekers S01 E06</title>
<link>https://clicknupload.co/xple0sskq2uh</link>
<thumbnail>https://i.imgur.com/ZCJA73Y.jpg</thumbnail>
<fanart></fanart>
</item>

<item>
<title>Truth Seekers S01 E07</title>
<link>https://clicknupload.co/ouo2rq6w5qsm</link>
<thumbnail>https://i.imgur.com/wlEnrec.jpg</thumbnail>
<fanart></fanart>
</item>

<item>
<title>Truth Seekers S01 E08</title>
<link>https://clicknupload.co/7a7qr4r9o8oj</link>
<thumbnail>https://i.imgur.com/wlEnrec.jpg</thumbnail>
<fanart></fanart>
</item>
