<item>
<title>Band of Brothers S01 E01</title>
<link>https://real-debrid.com/d/2FMOFGA6F3FL2</link>
<thumbnail>https://www.themoviedb.org/t/p/w600_and_h900_bestv2/pGzV187ogXzgJrvPRy2YPi29ofH.jpg</thumbnail>
<fanart>https://i.imgur.com/LC72IdN.jpg</fanart>
</item>

<item>
<title>Band of Brothers S01 E02</title>
<link>https://real-debrid.com/d/BXIFWG6ZZ7OOO</link>
<thumbnail>https://www.themoviedb.org/t/p/w600_and_h900_bestv2/pGzV187ogXzgJrvPRy2YPi29ofH.jpg</thumbnail>
<fanart>https://i.imgur.com/LC72IdN.jpg</fanart>
</item>

<item>
<title>Band of Brothers S01 E03</title>
<link>https://real-debrid.com/d/NGYX2FPIXE5NO</link>
<thumbnail>https://www.themoviedb.org/t/p/w600_and_h900_bestv2/pGzV187ogXzgJrvPRy2YPi29ofH.jpg</thumbnail>
<fanart>https://i.imgur.com/LC72IdN.jpg</fanart>
</item>

<item>
<title>Band of Brothers S01 E04</title>
<link>https://real-debrid.com/d/64EBCV4V7DJIQ</link>
<thumbnail>https://www.themoviedb.org/t/p/w600_and_h900_bestv2/pGzV187ogXzgJrvPRy2YPi29ofH.jpg</thumbnail>
<fanart>https://i.imgur.com/LC72IdN.jpg</fanart>
</item>

<item>
<title>Band of Brothers S01 E05</title>
<link>https://real-debrid.com/d/MJUU77IJE76VO</link>
<thumbnail>https://www.themoviedb.org/t/p/w600_and_h900_bestv2/pGzV187ogXzgJrvPRy2YPi29ofH.jpg</thumbnail>
<fanart>https://i.imgur.com/LC72IdN.jpg</fanart>
</item>

<item>
<title>Band of Brothers S01 E06</title>
<link>https://real-debrid.com/d/LPLPQX2CIKSQC</link>
<thumbnail>https://www.themoviedb.org/t/p/w600_and_h900_bestv2/pGzV187ogXzgJrvPRy2YPi29ofH.jpg</thumbnail>
<fanart>https://i.imgur.com/LC72IdN.jpg</fanart>
</item>

<item>
<title>Band of Brothers S01 E07</title>
<link>https://real-debrid.com/d/4OXXTXM7GSDAK</link>
<thumbnail>https://www.themoviedb.org/t/p/w600_and_h900_bestv2/pGzV187ogXzgJrvPRy2YPi29ofH.jpg</thumbnail>
<fanart>https://i.imgur.com/LC72IdN.jpg</fanart>
</item>

<item>
<title>Band of Brothers S01 E08</title>
<link>https://real-debrid.com/d/C5CKOGDWZT6ZC</link>
<thumbnail>https://www.themoviedb.org/t/p/w600_and_h900_bestv2/pGzV187ogXzgJrvPRy2YPi29ofH.jpg</thumbnail>
<fanart>https://i.imgur.com/LC72IdN.jpg</fanart>
</item>

<item>
<title>Band of Brothers S01 E09</title>
<link>https://real-debrid.com/d/NANLVLHVEX5BW</link>
<thumbnail>https://www.themoviedb.org/t/p/w600_and_h900_bestv2/pGzV187ogXzgJrvPRy2YPi29ofH.jpg</thumbnail>
<fanart>https://i.imgur.com/LC72IdN.jpg</fanart>
</item>

<item>
<title>Band of Brothers S01 E10</title>
<link>https://real-debrid.com/d/4GNE7J42BPNMC</link>
<thumbnail>https://www.themoviedb.org/t/p/w600_and_h900_bestv2/pGzV187ogXzgJrvPRy2YPi29ofH.jpg</thumbnail>
<fanart>https://i.imgur.com/LC72IdN.jpg</fanart>
</item>

<item>
<title>Band of Brothers Documentary</title>
<link>https://real-debrid.com/d/ZNIKYXCLNVZBW</link>
<thumbnail>https://www.themoviedb.org/t/p/w600_and_h900_bestv2/pGzV187ogXzgJrvPRy2YPi29ofH.jpg</thumbnail>
<fanart>https://i.imgur.com/LC72IdN.jpg</fanart>
</item>
