<item>
<title>[COLORblue][B]****Links Updated****[/B][/COLOR]</title>
<link>ignoreme</link>
<thumbnail>https://i.imgur.com/r6nMlcQ.png</thumbnail>
<fanart></fanart>
</item>

<item>
<title>A Discovery of Witches S02 E01</title>
<link>https://streamtape.com/v/agAVALGw9PUx81w/A.Discovery.of.Witches.S02E01.720p.WEBRip.x264-GalaxyTV.mkv.mp4</link>
<thumbnail>https://i.imgur.com/pczLUdj.jpg</thumbnail>
<fanart></fanart>
</item>

<item>
<title>A Discovery of Witches S02 E02</title>
<link>https://streamtape.com/v/616vByVmYJi9jop/A.Discovery.of.Witches.S02E02.720p.WEBRip.x264-GalaxyTV.mkv.mp4</link>
<thumbnail>https://i.imgur.com/pczLUdj.jpg</thumbnail>
<fanart></fanart>
</item>

<item>
<title>A Discovery of Witches S02 E03</title>
<link>https://streamtape.com/v/g2orQpZqDJfqW2O/A.Discovery.of.Witches.S02E03.720p.WEBRip.x264-GalaxyTV.mkv.mp4</link>
<thumbnail>https://i.imgur.com/pczLUdj.jpg</thumbnail>
<fanart></fanart>
</item>

<item>
<title>A Discovery of Witches S02 E04</title>
<link>https://streamtape.com/v/qZ6J394oDauz2Dv/A.Discovery.of.Witches.S02E04.720p.WEBRip.x264-GalaxyTV.mkv.mp4</link>
<thumbnail>https://i.imgur.com/pczLUdj.jpg</thumbnail>
<fanart></fanart>
</item>

<item>
<title>A Discovery of Witches S02 E05</title>
<link>https://streamtape.com/v/xMYL3AX2QVukrRl/A.Discovery.of.Witches.S02E05.720p.WEBRip.x264-GalaxyTV.mkv.mp4</link>
<thumbnail>https://i.imgur.com/pczLUdj.jpg</thumbnail>
<fanart></fanart>
</item>

<item>
<title>A Discovery of Witches S02 E06</title>
<link>https://streamtape.com/v/09lKOAQKz9iDmk/A.Discovery.of.Witches.S02E06.720p.WEBRip.x264-GalaxyTV.mkv.mp4</link>
<thumbnail>https://i.imgur.com/pczLUdj.jpg</thumbnail>
<fanart></fanart>
</item>

<item>
<title>A Discovery of Witches S02 E07</title>
<link>https://streamtape.com/v/z6llrJLVwlcYRdp/A.Discovery.of.Witches.S02E07.720p.WEBRip.x264-GalaxyTV.mkv.mp4</link>
<thumbnail>https://i.imgur.com/pczLUdj.jpg</thumbnail>
<fanart></fanart>
</item>

<item>
<title>A Discovery of Witches S02 E08</title>
<link>https://streamtape.com/v/3Jzgd9qG8acdylp/A.Discovery.of.Witches.S02E08.720p.WEBRip.x264-GalaxyTV.mkv</link>
<thumbnail>https://i.imgur.com/pczLUdj.jpg</thumbnail>
<fanart></fanart>
</item>

<item>
<title>A Discovery of Witches S02 E09</title>
<link>https://streamtape.com/v/7q7Ax3vBwkHJAR/A.Discovery.of.Witches.S02E09.720p.WEBRip.x264-GalaxyTV.mkv.mp4</link>
<thumbnail>https://i.imgur.com/pczLUdj.jpg</thumbnail>
<fanart></fanart>
</item>

<item>
<title>A Discovery of Witches S02 E10</title>
<link>https://streamtape.com/v/VO0VaXyXzmfKr29/A.Discovery.of.Witches.S02E10.720p.WEBRip.x264-GalaxyTV.mkv.mp4</link>
<thumbnail>https://i.imgur.com/pczLUdj.jpg</thumbnail>
<fanart></fanart>
</item>
